<?xml version="1.0" encoding="utf-8"?>
<odoo>
    <menuitem
            id="mail.menu_root_discuss"
            name="Chat"
            action="mail.action_discuss"
            web_icon="web_icon_change,static/description/chat.png"
            groups="base.group_user"
            sequence="1"
    />
    <menuitem id="sale.sale_menu_root"
              name="Sales"
              web_icon="web_icon_change,static/description/sales.png"
              active="True"
              sequence="7"/>

    <menuitem name="Website"
              id="website.menu_website_configuration"
              sequence="9"
              groups="base.group_user"
              web_icon="web_icon_change,static/description/website.png"/>

    <menuitem
        id="stock_barcode.stock_barcode_menu"
        action="stock_barcode.stock_barcode_action_main_menu"
        web_icon="web_icon_change,static/description/barcode.png"
        sequence="50"
        groups="stock.group_stock_user" />

    <menuitem
        id="quality_control.menu_quality_root"
        name="Quality"
        web_icon="web_icon_change,static/description/QC.png"
        sequence="51"
        groups="quality.group_quality_user"/>

    <menuitem
            id="point_of_sale.menu_point_root"
            name="P-Sales"
            groups="point_of_sale.group_pos_manager,point_of_sale.group_pos_user"
            web_icon="web_icon_change,static/description/p-sales.png"
            sequence="20"/>

    <menuitem name="Inventory" id="stock.menu_stock_root" sequence="30"
              groups="stock.group_stock_manager,stock.group_stock_user"
              web_icon="web_icon_change,static/description/inventory.png"/>

    <menuitem id="base.menu_management" name="Options" sequence="310"
              web_icon="web_icon_change,static/description/options.png"
              groups="base.group_system"/>

    <menuitem name="Setup"
              id="base.menu_administration"
              web_icon="web_icon_change,static/description/Setup.png"
              sequence="500"
              groups="base.group_erp_manager"/>

    <menuitem id="sign.menu_document" name="Sign" web_icon="web_icon_change,static/description/E_Sign.png" groups="sign.group_sign_employee"/>

    <menuitem name="Purchase"
              id="purchase.menu_purchase_root"
              groups="purchase.group_purchase_manager,purchase.group_purchase_user"
              web_icon="web_icon_change,static/description/Purchase.png"
              sequence="25"/>

    <menuitem
            id="hr.menu_hr_root"
            name="Our Team"
            groups="hr.group_hr_manager,hr.group_hr_user,base.group_user"
            web_icon="web_icon_change,static/description/Our_Team.png"
            sequence="75"/>

    <menuitem id="hr_attendance.menu_hr_attendance_root" name="C-Time" sequence="90"
              groups="hr_attendance.group_hr_attendance,hr_attendance.group_hr_attendance_kiosk"
              web_icon="web_icon_change,static/description/C-Time.png"/>

    <menuitem name="Contacts"
              id="contacts.menu_contacts"
              sequence="4"
              web_icon="web_icon_change,static/description/contacts.png"
              groups="base.group_user,base.group_partner_manager"/>

    <menuitem
            id="calendar.mail_menu_calendar"
            name="Calendar"
            sequence="2"
            action="calendar.action_calendar_event"
            web_icon="web_icon_change,static/description/calendar.png"
            groups="base.group_user"/>

    <menuitem
            name="Off Clock"
            id="hr_holidays.menu_hr_holidays_root"
            sequence="95"
            web_icon="web_icon_change,static/description/Off_Clock.png"
            groups="base.group_user"/>

    <menuitem id="base.menu_board_root" name="KPI" sequence="305"
              web_icon="web_icon_change,static/description/KPI.png" groups="base.group_user"/>

    <menuitem name="Vehicles" id="fleet.menu_root" sequence="115" groups="fleet.fleet_group_user"
              web_icon="web_icon_change,static/description/Vehicles.png"/>

    <menuitem name="Project"
              id="project.menu_main_pm"
              groups="project.group_project_manager,project.group_project_user"
              web_icon="web_icon_change,static/description/Project.png"
              sequence="50"/>

    <menuitem id="hr_expense.menu_hr_expense_root" name="Exp-Reports" sequence="100"
              web_icon="web_icon_change,static/description/Exp-Reports.png"/>

    <menuitem id="hr_timesheet.timesheet_menu_root"
            name="Timesheets"
            sequence="55"
            groups="hr_timesheet.group_hr_timesheet_user"
            web_icon="web_icon_change,static/description/timesheet.png"/>

    <menuitem name="Staff Surveys"
              id="survey.menu_surveys"
              sequence="70"
              groups="survey.group_survey_user"
              web_icon="web_icon_change,static/description/Staff_Survey.png"/>

    <menuitem
            id="crm.crm_menu_root"
            name="CRM"
            web_icon="web_icon_change,static/description/CRM.png"
            groups="sales_team.group_sale_salesman,sales_team.group_sale_manager"
            sequence="6"/>

    <menuitem name="E-Learn"
              id="website_slides.website_slides_menu_root"
              web_icon="web_icon_change,static/description/e-learning-1.png"
              groups="website_slides.group_website_slides_officer"
              action="website_slides.slide_channel_action_overview"/>

    <menuitem name="M-Events"
              id="event.event_main_menu"
              sequence="65"
              groups="event.group_event_user"
              web_icon="web_icon_change,static/description/M-Events.png"/>

    <menuitem id="mrp.menu_mrp_root"
              name="Build It"
              groups="mrp.group_mrp_user,mrp.group_mrp_manager"
              web_icon="web_icon_change,static/description/Build_It.png"
              sequence="35">

        <menuitem id="mrp.menu_mrp_manufacturing"
                  name="Operations"
                  sequence="10"/>

        <menuitem id="mrp.mrp_planning_menu_root"
                  name="Planning"
                  sequence="15"/>

        <menuitem id="mrp.menu_mrp_bom"
                  name="Products"
                  sequence="20"/>

        <menuitem id="mrp.menu_mrp_reporting"
                  name="Reporting"
                  sequence="25"/>

        <menuitem id="mrp.menu_mrp_configuration"
                  name="Configuration"
                  groups="mrp.group_mrp_manager"
                  sequence="100"/>
    </menuitem>

    <menuitem
            id="maintenance.menu_maintenance_title"
            name="S Service"
            web_icon="web_icon_change,static/description/S_Service.png"
            sequence="110"/>

    <menuitem name="M Email" id="mass_mailing.mass_mailing_menu_root" sequence="60"
              web_icon="web_icon_change,static/description/M_Email.png"/>

    <menuitem name="My Dashboard" id="ks_dashboard_ninja.board_menu_root"
                  web_icon="web_icon_change,static/description/KPI.png"
                  action="ks_dashboard_ninja.board_dashboard_action_window"/>

    <menuitem
            id="note.menu_note_notes"
            name="Notes"
            sequence="3"
            action="note.action_note_note"
            web_icon="web_icon_change,static/description/Notes.png">
        <menuitem
                id="note.menu_note_configuration"
                name="Configuration"
                sequence="100"
                groups="base.group_no_one">
            <menuitem
                    id="note.menu_notes_stage"
                    name="Stages"
                    action="note.action_note_stage"
                    sequence="21"/>
            <menuitem
                    id="note.notes_tag_menu"
                    action="note.note_tag_action"
                    sequence="22"/>
        </menuitem>
    </menuitem>

    <menuitem id="mass_mailing_sms.mass_mailing_sms_menu_root"
              name="SMS Marketing"
              sequence="60"
              web_icon="web_icon_change,static/description/M_Text.png"
              groups="mass_mailing.group_mass_mailing_user"/>

    <menuitem
            id="im_livechat.menu_livechat_root"
            name="L-Chat"
            web_icon="web_icon_change,static/description/l-chat.png"
            groups="im_livechat.im_livechat_group_user"
            sequence="205"/>

    <menuitem
            name="Recruitment"
            id="hr_recruitment.menu_hr_recruitment_root"
            web_icon="web_icon_change,static/description/Recruitment.png"
            groups="hr_recruitment.group_hr_recruitment_user"
            sequence="80"/>

    <menuitem id="utm.menu_link_tracker_root"
        name="Link Tracker"
        sequence="30"
        web_icon="web_icon_change,static/description/Link_Tracker.png"
        groups="base.group_no_one"/>

    <menuitem id="account.menu_finance" name="The Books" web_icon="web_icon_change,static/description/The_Books.png"/>

    <menuitem id='lunch.menu_lunch' name='Food' sequence="105" groups="lunch.group_lunch_user"
              web_icon="web_icon_change,static/description/Food.png">
        <menuitem name="My Lunch" id="lunch.menu_lunch_title" sequence="50">
            <menuitem name="New Order" id="lunch.lunch_order_menu_form" action="lunch.lunch_product_action_order"
                      sequence="1"/>
            <menuitem name="My Order History" id="lunch.lunch_order_menu_tree" action="lunch.lunch_order_action"
                      sequence="2"/>
            <menuitem name="My Account History" id="lunch.lunch_cashmove_report_menu_form"
                      action="lunch.lunch_cashmove_report_action_account" sequence="3"/>
        </menuitem>
        <menuitem name="Manager" id="lunch.menu_lunch_admin" sequence="51" groups="lunch.group_lunch_manager">
            <menuitem name="Today's Orders" id="lunch.lunch_order_menu_by_supplier"
                      action="lunch.lunch_order_action_by_supplier"/>
            <menuitem name="Control Vendors" id="lunch.lunch_order_menu_control_suppliers"
                      action="lunch.lunch_order_action_control_suppliers"/>
            <menuitem name="Control Accounts" id="lunch.lunch_cashmove_report_menu_control_accounts"
                      action="lunch.lunch_cashmove_report_action_control_accounts"/>
            <menuitem name="Cash Moves" id="lunch.lunch_cashmove_report_menu_payment"
                      action="lunch.lunch_cashmove_action_payment"/>
        </menuitem>
        <menuitem name="Configuration" id="lunch.menu_lunch_config" sequence="53" groups="lunch.group_lunch_manager">
            <menuitem name="Settings" id="lunch.lunch_settings_menu" action="lunch.lunch_config_settings_action"
                      sequence="1"/>
            <menuitem name="Vendors" id="lunch.lunch_vendors_menu" action="lunch.lunch_vendors_action" sequence="2"/>
            <menuitem name="Locations" id="lunch.lunch_location_menu" action="lunch.lunch_location_action"
                      sequence="3"/>
            <menuitem name="Products" id="lunch.lunch_product_menu" action="lunch.lunch_product_action" sequence="4"/>
            <menuitem name="Product Categories" id="lunch.lunch_product_category_menu"
                      action="lunch.lunch_product_category_action"
                      sequence="5"/>
            <menuitem name="Alerts" id="lunch.lunch_alert_menu" action="lunch.lunch_alert_action" sequence="6"/>
        </menuitem>
    </menuitem>
</odoo>
